{"place":{"id":51192,"name":"La Taverna","description":null,"sharedLink":"https://eda.yandex/restaurant/La_Taverna?utm_source=rst_shared_link&utm_medium=referral&utm_campaign=web","slug":"La_Taverna","market":false,"tags":[{"id":115,"name":"Европейская"},{"id":501,"name":"Средиземноморская"},{"id":34,"name":"Пицца"}],"priceCategory":{"id":3,"name":"₽₽₽","value":1},"rating":null,"minimalOrderPrice":0,"minimalDeliveryCost":0,"isNew":false,"isStore":false,"promo":[],"promos":[],"address":{"location":{"latitude":55.758352,"longitude":37.555364},"short":"Шмитовский проезд, 3с1А","city":"Москва"},"picture":{"uri":"/images/places/fa13/1370147-fa1305e5abffd94a85b9016329a2bab0-{w}x{h}.jpeg","ratio":1.33},"isPromoAvailable":false,"personalizationStrategy":null,"footerDescription":"Исполнитель (продавец): ООО\"Эллада\", 129110,г Москва,Проспект мира,дом48,стр 6, ИНН 7702810707, рег.номер 1137746208522.<br>Режим работы ресторана: с 12:00 до 23:00","availablePaymentMethods":[1,2],"deliveryConditions":"Доставка 39 ₽ на заказ от 500 ₽","promoTypes":[],"type":null},"locationParams":null,"surge":null}