{"place":{"id":52371,"name":"Ламянь","description":null,"sharedLink":"https://eda.yandex/restaurant/lamyan?utm_source=rst_shared_link&utm_medium=referral&utm_campaign=web","slug":"lamyan","market":false,"tags":[{"id":7,"name":"Китайская"},{"id":645,"name":"Фудмолл «Депо»"}],"priceCategory":{"id":2,"name":"₽₽","value":0.5},"rating":null,"minimalOrderPrice":0,"minimalDeliveryCost":0,"isNew":false,"isStore":false,"promo":[],"promos":[],"address":{"location":{"latitude":55.780213,"longitude":37.593075},"short":"Лесная улица, 20с3","city":"Москва"},"picture":{"uri":"/images/places/a990/1380298-a9904e41bebd0c47f88fc1d80cf7767e-{w}x{h}.jpeg","ratio":1.33},"isPromoAvailable":false,"personalizationStrategy":null,"footerDescription":"Исполнитель (продавец): ООО Ламянь, 101000, г. Москва, ул. Мясницкая, д. 41, стр.5, этаж 4, каб. №8, ИНН 7708332951, рег.номер 1187746582385.<br>Режим работы ресторана: с 10:00 до 22:00","availablePaymentMethods":[1,2],"deliveryConditions":"Доставка 39-99 ₽. Бесплатно при заказе от 1500 ₽","promoTypes":[],"type":null},"locationParams":null,"surge":null}