{"place":{"id":127,"name":"China Club","description":null,"sharedLink":"https://eda.yandex/restaurant/china_club?utm_source=rst_shared_link&utm_medium=referral&utm_campaign=web","slug":"china_club","market":false,"tags":[{"id":58,"name":"Паназиатская"},{"id":626,"name":"Вок"}],"priceCategory":{"id":3,"name":"₽₽₽","value":1},"rating":4.9,"minimalOrderPrice":0,"minimalDeliveryCost":0,"isNew":false,"isStore":false,"promo":[],"promos":[],"address":{"location":{"latitude":55.768694,"longitude":37.586104},"short":"улица Красина, 21","city":"Москва"},"picture":{"uri":"/images/places/11bf/1370147-11bf4d94f79abf51ec1a5c7371d3a17e-{w}x{h}.jpeg","ratio":1.33},"isPromoAvailable":false,"personalizationStrategy":null,"footerDescription":"Исполнитель (продавец): ООО \"ИНТЕЛЛИ\", 123056, Москва г, Красина ул, дом № 21, ИНН 7728247687, рег.номер 1027700494348.<br>Режим работы ресторана: с 12:00 до 22:30","availablePaymentMethods":[1,2],"deliveryConditions":"Доставка 39-99 ₽. Бесплатно при заказе от 2000 ₽","promoTypes":[],"type":null},"locationParams":null,"surge":null}