{"description":{"payload":{"foundPlace":{"place":{"id":143,"name":"Профессор Пуф","description":null,"sharedLink":"https://eda.yandex/restaurant/Professor_Puf?utm_source=rst_shared_link&utm_medium=referral&utm_campaign=web","slug":"Professor_Puf","market":false,"tags":[{"id":40,"name":"Домашняя"},{"id":8,"name":"Русская"},{"id":593,"name":"Выпечка"},{"id":235,"name":"Завтраки"},{"id":569,"name":"Бургеры"}],"priceCategory":{"id":2,"name":"₽₽","value":0.5},"rating":4.6,"minimalOrderPrice":0,"minimalDeliveryCost":0,"isNew":false,"isStore":false,"promo":[],"promos":[],"address":{"location":{"latitude":55.747089,"longitude":37.607628},"short":"улица Волхонка, 9с1","city":"Москва"},"picture":{"uri":"/images/places/40e9/1368744-40e95a946eef6bed5cc31cec4f770e54-{w}x{h}.jpeg","ratio":1.33},"isPromoAvailable":false,"personalizationStrategy":null,"footerDescription":"Исполнитель (продавец): ООО \"ПРОФЕССОР ПУФ\", 105066, Москва г, Спартаковская ул, дом № 19, строение 3А, этаж 1, помещение 118, офис 2В, ИНН 9701022425, рег.номер 5157746096888.<br>Режим работы ресторана: с 10:00 до 21:30","availablePaymentMethods":[1,2],"deliveryConditions":"Доставка 39 ₽ на заказ от 500 ₽","promoTypes":[],"type":null},"locationParams":null,"surge":null},"availableTimePicker":[[],[]]}},"menu":{"payload":{"categories":[{"id":null,"name":"Популярные блюда","schedule":null,"available":true,"items":[{"id":18583,"name":"Тыква, маринованная в облепиховом соке","description":"Со свеклой и брынзой","available":true,"inStock":null,"price":399,"promoPrice":null,"optionsGroups":[],"picture":{"uri":"/images/menu/032c/1370147-032cb19f7b1752f1f38e54e43d1090f1-{w}x{h}.jpeg","ratio":1.5},"weight":"270 г","promoTypes":[]},{"id":160014,"name":"Суп Юшка Кубанская","description":"На красном бульоне с говядиной и мясной лапшой","available":true,"inStock":null,"price":399,"promoPrice":null,"optionsGroups":[],"picture":{"uri":"/images/menu/6e4d/1380157-6e4d455191f70f8a677a8f94b0325b75-{w}x{h}.jpeg","ratio":1.5},"weight":"530 г","promoTypes":[]},{"id":160042,"name":"Паштет из печени цыплёнка","description":null,"available":true,"inStock":null,"price":319,"promoPrice":null,"optionsGroups":[],"picture":{"uri":"/images/menu/cb0a/1387779-cb0a69e1cb29e96bdd257d34b8953dda-{w}x{h}.jpeg","ratio":1.5},"weight":"270 г","promoTypes":[]},{"id":305974,"name":"Бефстроганов","description":"С печёным картофелем","available":true,"inStock":null,"price":569,"promoPrice":null,"optionsGroups":[],"picture":null,"weight":"320 г","promoTypes":[]}],"categories":[]},{"id":1730,"name":"Завтрак","schedule":"до 12:00","available":false,"items":[{"id":18574,"name":"Оладьи ржаные","description":"С персиком и черносливом","available":false,"inStock":null,"price":239,"promoPrice":null,"optionsGroups":[],"picture":{"uri":"/images/menu/8c63/1387779-8c636882c2a95f66073d3e858f5e4afd-{w}x{h}.jpeg","ratio":1.5},"weight":"230 г","promoTypes":[]},{"id":46702,"name":"Омлет на льняной вафле с лососем под соусом голландез","description":"Рукодельные вафли, лосось, омлет","available":false,"inStock":null,"price":359,"promoPrice":null,"optionsGroups":[],"picture":{"uri":"/images/menu/5bba/1380298-5bbac8862d6b151fb544c9fbb3530b92-{w}x{h}.jpeg","ratio":1.5},"weight":"480 г","promoTypes":[]},{"id":500431,"name":"Оладыши","description":"Творог в блине","available":false,"inStock":null,"price":259,"promoPrice":null,"optionsGroups":[],"picture":{"uri":"/images/menu/6827/1380298-6827778a32b8544e71952764a9477df3-{w}x{h}.jpeg","ratio":1.5},"weight":"200 г","promoTypes":[]},{"id":500439,"name":"Блинчики в ассортименте","description":"Со сметаной, вареньем или медом на выбор","available":false,"inStock":null,"price":219,"promoPrice":null,"optionsGroups":[{"id":62543,"name":"На выбор","options":[{"id":417889,"name":"Варенье","price":0,"promoPrice":null,"multiplier":1},{"id":1056213,"name":"Мёд","price":0,"promoPrice":null,"multiplier":1},{"id":1056215,"name":"Сметана","price":0,"promoPrice":null,"multiplier":1}],"required":true,"minSelected":1,"maxSelected":1}],"picture":null,"weight":"155 г","promoTypes":[]},{"id":500441,"name":"Глазунья c чоризо","description":"На льняном тосте","available":false,"inStock":null,"price":249,"promoPrice":null,"optionsGroups":[],"picture":null,"weight":"250 г","promoTypes":[]},{"id":901017,"name":"Каша овсяная","description":"С яблоком и кардамоном","available":false,"inStock":null,"price":189,"promoPrice":null,"optionsGroups":[],"picture":null,"weight":"250 г","promoTypes":[]}],"categories":[]},{"id":1732,"name":"Салаты","schedule":null,"available":true,"items":[{"id":18583,"name":"Тыква, маринованная в облепиховом соке","description":"Со свеклой и брынзой","available":true,"inStock":null,"price":399,"promoPrice":null,"optionsGroups":[],"picture":{"uri":"/images/menu/032c/1370147-032cb19f7b1752f1f38e54e43d1090f1-{w}x{h}.jpeg","ratio":1.5},"weight":"270 г","promoTypes":[]},{"id":189229,"name":"Салат с печёной говядиной","description":"С проростками сои","available":true,"inStock":null,"price":559,"promoPrice":null,"optionsGroups":[],"picture":{"uri":"/images/menu/378e/1380298-378e07b1c70a00f081e3952f95445a1f-{w}x{h}.jpeg","ratio":1.5},"weight":"250 г","promoTypes":[]},{"id":305971,"name":"Салат из Кубанских синеньких баклажанов","description":"С копчёной сливой","available":true,"inStock":null,"price":379,"promoPrice":null,"optionsGroups":[],"picture":null,"weight":"250 г","promoTypes":[]},{"id":305972,"name":"Салат Цезарь а-ля Пуф","description":"С курицей","available":true,"inStock":null,"price":479,"promoPrice":null,"optionsGroups":[],"picture":null,"weight":"247 г","promoTypes":[]}],"categories":[]},{"id":1735,"name":"Закуски","schedule":null,"available":true,"items":[{"id":160042,"name":"Паштет из печени цыплёнка","description":null,"available":true,"inStock":null,"price":319,"promoPrice":null,"optionsGroups":[],"picture":{"uri":"/images/menu/cb0a/1387779-cb0a69e1cb29e96bdd257d34b8953dda-{w}x{h}.jpeg","ratio":1.5},"weight":"270 г","promoTypes":[]},{"id":901021,"name":"Копченые креветки","description":"В перечном соусе","available":true,"inStock":null,"price":469,"promoPrice":null,"optionsGroups":[],"picture":null,"weight":"310 г","promoTypes":[]},{"id":1106221,"name":"Икра из авокадо","description":null,"available":true,"inStock":null,"price":379,"promoPrice":null,"optionsGroups":[],"picture":null,"weight":"75 г","promoTypes":[]},{"id":1106223,"name":"Форшмак из сельди домашнего посола","description":null,"available":true,"inStock":null,"price":359,"promoPrice":null,"optionsGroups":[],"picture":null,"weight":"75 г","promoTypes":[]}],"categories":[]},{"id":13091,"name":"Супы","schedule":null,"available":true,"items":[{"id":160009,"name":"Суп Юшка Курильская","description":"На рыбном бульоне с лососем, черной лапшой и ракушками","available":true,"inStock":null,"price":429,"promoPrice":null,"optionsGroups":[],"picture":{"uri":"/images/menu/7eeb/1380298-7eeb841609b2848e42d69f3982039d50-{w}x{h}.jpeg","ratio":1.5},"weight":"520 г","promoTypes":[]},{"id":160014,"name":"Суп Юшка Кубанская","description":"На красном бульоне с говядиной и мясной лапшой","available":true,"inStock":null,"price":399,"promoPrice":null,"optionsGroups":[],"picture":{"uri":"/images/menu/6e4d/1380157-6e4d455191f70f8a677a8f94b0325b75-{w}x{h}.jpeg","ratio":1.5},"weight":"530 г","promoTypes":[]},{"id":343457,"name":"Суп Юшка Майкопская","description":"На курином бульоне с индюшкой и кукурузной лапшой","available":true,"inStock":null,"price":399,"promoPrice":null,"optionsGroups":[],"picture":{"uri":"/images/menu/ef7a/1370147-ef7af124fe6a7f84f5ea5dbe7c8b659a-{w}x{h}.jpeg","ratio":1.5},"weight":"505 г","promoTypes":[]},{"id":169191,"name":"Крем-суп из белых грибов","description":null,"available":true,"inStock":null,"price":399,"promoPrice":null,"optionsGroups":[],"picture":null,"weight":"325 г","promoTypes":[]}],"categories":[]},{"id":1734,"name":"Горячие блюда","schedule":null,"available":true,"items":[{"id":18593,"name":"Сайра из Охотского моря","description":"Под соусом из чёрного перца","available":true,"inStock":null,"price":599,"promoPrice":null,"optionsGroups":[],"picture":{"uri":"/images/menu/7d6b/1380157-7d6b78093c9d35f9788d931ee2e3ebe5-{w}x{h}.jpeg","ratio":1.25},"weight":"450 г","promoTypes":[]},{"id":305975,"name":"Бургер с магаданской олениной","description":"С печеной грушей конференц","available":true,"inStock":null,"price":599,"promoPrice":null,"optionsGroups":[],"picture":null,"weight":"430 г","promoTypes":[]},{"id":305974,"name":"Бефстроганов","description":"С печёным картофелем","available":true,"inStock":null,"price":569,"promoPrice":null,"optionsGroups":[],"picture":null,"weight":"320 г","promoTypes":[]},{"id":305976,"name":"Ляпун с белыми грибами под сметанным соусом","description":"С трюфельным маслом","available":true,"inStock":null,"price":420,"promoPrice":null,"optionsGroups":[{"id":162259,"name":"Дополнительно","options":[{"id":1410277,"name":"Белые грибы","price":150,"promoPrice":null,"multiplier":1},{"id":1410279,"name":"Трюфельное масло","price":120,"promoPrice":null,"multiplier":1},{"id":1410281,"name":"Вяленые томаты","price":250,"promoPrice":null,"multiplier":1},{"id":1410283,"name":"Ростбиф","price":250,"promoPrice":null,"multiplier":1},{"id":1410285,"name":"Бекон","price":99,"promoPrice":null,"multiplier":1},{"id":2683305,"name":"Чоризо","price":99,"promoPrice":null,"multiplier":1},{"id":2683307,"name":"Копченая курица","price":150,"promoPrice":null,"multiplier":1},{"id":2683309,"name":"Пармезан","price":150,"promoPrice":null,"multiplier":1},{"id":2683311,"name":"Лук красный","price":50,"promoPrice":null,"multiplier":1},{"id":2683313,"name":"Сальса из помидоров","price":120,"promoPrice":null,"multiplier":1},{"id":2683315,"name":"Халапеньо","price":99,"promoPrice":null,"multiplier":1},{"id":2683317,"name":"Оливки","price":120,"promoPrice":null,"multiplier":1},{"id":2683319,"name":"Маринованный кабачок","price":99,"promoPrice":null,"multiplier":1},{"id":2683321,"name":"Помидоры черри","price":120,"promoPrice":null,"multiplier":1},{"id":2683323,"name":"Моцарелла","price":99,"promoPrice":null,"multiplier":1},{"id":2683325,"name":"Креветки","price":250,"promoPrice":null,"multiplier":1},{"id":2683327,"name":"Запеченный перец","price":99,"promoPrice":null,"multiplier":1},{"id":2683329,"name":"Руккола","price":99,"promoPrice":null,"multiplier":1},{"id":2683331,"name":"Сливочный соус","price":120,"promoPrice":null,"multiplier":1},{"id":2683333,"name":"Томатный соус","price":99,"promoPrice":null,"multiplier":1},{"id":2683335,"name":"Перечный соус","price":150,"promoPrice":null,"multiplier":1},{"id":2683337,"name":"Салат фризе","price":99,"promoPrice":null,"multiplier":1}],"required":false,"minSelected":0,"maxSelected":22}],"picture":null,"weight":"220 г","promoTypes":[]},{"id":1987821,"name":"Ляпун с говяжьим боком","description":"Под перечным соусом","available":true,"inStock":null,"price":420,"promoPrice":null,"optionsGroups":[{"id":326873,"name":"Дополнительно","options":[{"id":2683339,"name":"Белые грибы","price":150,"promoPrice":null,"multiplier":1},{"id":2683341,"name":"Трюфельное масло","price":120,"promoPrice":null,"multiplier":1},{"id":2683343,"name":"Вяленые томаты","price":250,"promoPrice":null,"multiplier":1},{"id":2683345,"name":"Ростбиф","price":250,"promoPrice":null,"multiplier":1},{"id":2683347,"name":"Бекон","price":99,"promoPrice":null,"multiplier":1},{"id":2683349,"name":"Чоризо","price":99,"promoPrice":null,"multiplier":1},{"id":2683351,"name":"Копченая курица","price":150,"promoPrice":null,"multiplier":1},{"id":2683353,"name":"Пармезан","price":150,"promoPrice":null,"multiplier":1},{"id":2683355,"name":"Лук красный","price":50,"promoPrice":null,"multiplier":1},{"id":2683357,"name":"Сальса из помидоров","price":120,"promoPrice":null,"multiplier":1},{"id":2683359,"name":"Халапеньо","price":99,"promoPrice":null,"multiplier":1},{"id":2683361,"name":"Оливки","price":120,"promoPrice":null,"multiplier":1},{"id":2683363,"name":"Маринованный кабачок","price":99,"promoPrice":null,"multiplier":1},{"id":2683365,"name":"Помидоры черри","price":120,"promoPrice":null,"multiplier":1},{"id":2683367,"name":"Моцарелла","price":99,"promoPrice":null,"multiplier":1},{"id":2683369,"name":"Креветки","price":250,"promoPrice":null,"multiplier":1},{"id":2683371,"name":"Запеченный перец","price":99,"promoPrice":null,"multiplier":1},{"id":2683373,"name":"Руккола","price":99,"promoPrice":null,"multiplier":1},{"id":2683375,"name":"Сливочный соус","price":120,"promoPrice":null,"multiplier":1},{"id":2683377,"name":"Томатный соус","price":99,"promoPrice":null,"multiplier":1},{"id":2683379,"name":"Перечный соус","price":150,"promoPrice":null,"multiplier":1},{"id":2683381,"name":"Салат фризе","price":99,"promoPrice":null,"multiplier":1}],"required":false,"minSelected":0,"maxSelected":22}],"picture":null,"weight":"250 г","promoTypes":[]},{"id":901043,"name":"Бургер с говяжьим бифштексом и карамелизованным луком","description":null,"available":true,"inStock":null,"price":599,"promoPrice":null,"optionsGroups":[],"picture":null,"weight":"450 г","promoTypes":[]},{"id":1987827,"name":"Ляпун с сулугуни, томатами и кинзой","description":null,"available":true,"inStock":null,"price":390,"promoPrice":null,"optionsGroups":[{"id":326879,"name":"Дополнительно","options":[{"id":2683471,"name":"Белые грибы","price":150,"promoPrice":null,"multiplier":1},{"id":2683473,"name":"Трюфельное масло","price":120,"promoPrice":null,"multiplier":1},{"id":2683475,"name":"Вяленые томаты","price":250,"promoPrice":null,"multiplier":1},{"id":2683477,"name":"Ростбиф","price":250,"promoPrice":null,"multiplier":1},{"id":2683479,"name":"Бекон","price":99,"promoPrice":null,"multiplier":1},{"id":2683481,"name":"Чоризо","price":99,"promoPrice":null,"multiplier":1},{"id":2683483,"name":"Копченая курица","price":150,"promoPrice":null,"multiplier":1},{"id":2683485,"name":"Пармезан","price":150,"promoPrice":null,"multiplier":1},{"id":2683487,"name":"Лук красный","price":50,"promoPrice":null,"multiplier":1},{"id":2683489,"name":"Сальса из помидоров","price":120,"promoPrice":null,"multiplier":1},{"id":2683491,"name":"Халапеньо","price":99,"promoPrice":null,"multiplier":1},{"id":2683493,"name":"Оливки","price":120,"promoPrice":null,"multiplier":1},{"id":2683495,"name":"Маринованный кабачок","price":99,"promoPrice":null,"multiplier":1},{"id":2683497,"name":"Помидоры черри","price":120,"promoPrice":null,"multiplier":1},{"id":2683499,"name":"Моцарелла","price":99,"promoPrice":null,"multiplier":1},{"id":2683501,"name":"Креветки","price":250,"promoPrice":null,"multiplier":1},{"id":2683503,"name":"Запеченный перец","price":99,"promoPrice":null,"multiplier":1},{"id":2683505,"name":"Руккола","price":99,"promoPrice":null,"multiplier":1},{"id":2683507,"name":"Сливочный соус","price":120,"promoPrice":null,"multiplier":1},{"id":2683509,"name":"Томатный соус","price":99,"promoPrice":null,"multiplier":1},{"id":2683511,"name":"Перечный соус","price":150,"promoPrice":null,"multiplier":1},{"id":2683513,"name":"Салат фризе","price":99,"promoPrice":null,"multiplier":1}],"required":false,"minSelected":0,"maxSelected":22}],"picture":null,"weight":"200 г","promoTypes":[]},{"id":1987831,"name":"Ляпун с креветками, рукколой и русским песто","description":null,"available":true,"inStock":null,"price":599,"promoPrice":null,"optionsGroups":[{"id":326881,"name":"Дополнительно","options":[{"id":2683515,"name":"Белые грибы","price":150,"promoPrice":null,"multiplier":1},{"id":2683517,"name":"Трюфельное масло","price":120,"promoPrice":null,"multiplier":1},{"id":2683519,"name":"Вяленые томаты","price":250,"promoPrice":null,"multiplier":1},{"id":2683521,"name":"Ростбиф","price":250,"promoPrice":null,"multiplier":1},{"id":2683523,"name":"Бекон","price":99,"promoPrice":null,"multiplier":1},{"id":2683525,"name":"Чоризо","price":99,"promoPrice":null,"multiplier":1},{"id":2683527,"name":"Копченая курица","price":150,"promoPrice":null,"multiplier":1},{"id":2683529,"name":"Пармезан","price":150,"promoPrice":null,"multiplier":1},{"id":2683531,"name":"Лук красный","price":50,"promoPrice":null,"multiplier":1},{"id":2683533,"name":"Сальса из помидоров","price":120,"promoPrice":null,"multiplier":1},{"id":2683535,"name":"Халапеньо","price":99,"promoPrice":null,"multiplier":1},{"id":2683537,"name":"Оливки","price":120,"promoPrice":null,"multiplier":1},{"id":2683539,"name":"Маринованный кабачок","price":99,"promoPrice":null,"multiplier":1},{"id":2683541,"name":"Помидоры черри","price":120,"promoPrice":null,"multiplier":1},{"id":2683543,"name":"Моцарелла","price":99,"promoPrice":null,"multiplier":1},{"id":2683545,"name":"Креветки","price":250,"promoPrice":null,"multiplier":1},{"id":2683547,"name":"Запеченный перец","price":99,"promoPrice":null,"multiplier":1},{"id":2683549,"name":"Руккола","price":99,"promoPrice":null,"multiplier":1},{"id":2683551,"name":"Сливочный соус","price":120,"promoPrice":null,"multiplier":1},{"id":2683553,"name":"Томатный соус","price":99,"promoPrice":null,"multiplier":1},{"id":2683555,"name":"Перечный соус","price":150,"promoPrice":null,"multiplier":1},{"id":2683557,"name":"Салат фризе","price":99,"promoPrice":null,"multiplier":1}],"required":false,"minSelected":0,"maxSelected":22}],"picture":null,"weight":"250 г","promoTypes":[]}],"categories":[]},{"id":4069,"name":"Десерты","schedule":null,"available":true,"items":[{"id":46696,"name":"Десерт Витушка ореховая под темным шоколадом","description":null,"available":true,"inStock":null,"price":239,"promoPrice":null,"optionsGroups":[],"picture":{"uri":"/images/menu/a09e/1380298-a09ef4808e1481a97fbc5f16c7868b07-{w}x{h}.jpeg","ratio":1.25},"weight":"170 г","promoTypes":[]},{"id":46697,"name":"Десерт Витушка ореховая под белым шоколадом","description":null,"available":true,"inStock":null,"price":239,"promoPrice":null,"optionsGroups":[],"picture":{"uri":"/images/menu/c093/1387779-c09324f6a874ffaed6bc9581b13b4ca9-{w}x{h}.jpeg","ratio":1.25},"weight":"170 г","promoTypes":[]},{"id":46693,"name":"Круассан","description":"Классический или ржаной на выбор","available":true,"inStock":null,"price":110,"promoPrice":null,"optionsGroups":[{"id":336139,"name":"На выбор","options":[{"id":2723647,"name":"Классический","price":0,"promoPrice":null,"multiplier":1},{"id":2723649,"name":"Ржаной","price":40,"promoPrice":null,"multiplier":1}],"required":true,"minSelected":1,"maxSelected":1}],"picture":null,"weight":"75 г","promoTypes":[]},{"id":46695,"name":"Десерт Витушка с зелеными яблоками и корицей","description":null,"available":true,"inStock":null,"price":199,"promoPrice":null,"optionsGroups":[],"picture":null,"weight":"115 г","promoTypes":[]},{"id":160046,"name":"Миндальный круассан","description":null,"available":true,"inStock":null,"price":239,"promoPrice":null,"optionsGroups":[],"picture":null,"weight":"185 г","promoTypes":[]}],"categories":[]},{"id":16659,"name":"Напитки","schedule":null,"available":true,"items":[{"id":500983,"name":"Лимонад в ассортименте","description":"Облепиховый, черная смородина, огуречный, фейхоа, малина-маракуйя, личи, дюшес","available":true,"inStock":null,"price":280,"promoPrice":null,"optionsGroups":[{"id":62533,"name":"На выбор","options":[{"id":417843,"name":"Облепиховый","price":0,"promoPrice":null,"multiplier":1},{"id":417845,"name":"Черная смородина","price":0,"promoPrice":null,"multiplier":1},{"id":417847,"name":"Огуречный","price":0,"promoPrice":null,"multiplier":1},{"id":417849,"name":"Фейхоа","price":0,"promoPrice":null,"multiplier":1},{"id":417851,"name":"Малина-маракуйя","price":0,"promoPrice":null,"multiplier":1},{"id":417853,"name":"Личи","price":0,"promoPrice":null,"multiplier":1},{"id":417855,"name":"Дюшес","price":0,"promoPrice":null,"multiplier":1}],"required":true,"minSelected":1,"maxSelected":1}],"picture":null,"weight":"250 мл","promoTypes":[]},{"id":500985,"name":"Лимонад в ассортименте","description":"Облепиховый, черная смородина, огуречный, фейхоа, малина-маракуйя, личи, дюшес","available":true,"inStock":null,"price":660,"promoPrice":null,"optionsGroups":[{"id":62535,"name":"На выбор","options":[{"id":417857,"name":"Облепиховый","price":0,"promoPrice":null,"multiplier":1},{"id":417859,"name":"Черная смородина","price":0,"promoPrice":null,"multiplier":1},{"id":417861,"name":"Огуречный","price":0,"promoPrice":null,"multiplier":1},{"id":417863,"name":"Фейхоа","price":0,"promoPrice":null,"multiplier":1},{"id":417865,"name":"Малина-маракуйя","price":0,"promoPrice":null,"multiplier":1},{"id":417867,"name":"Личи","price":0,"promoPrice":null,"multiplier":1},{"id":417869,"name":"Дюшес","price":0,"promoPrice":null,"multiplier":1}],"required":true,"minSelected":1,"maxSelected":1}],"picture":null,"weight":"900 мл","promoTypes":[]},{"id":500987,"name":"Домашний бородинский хлебный квас","description":"Объем на выбор","available":true,"inStock":null,"price":170,"promoPrice":null,"optionsGroups":[{"id":1440946,"name":"Объем на выбор","options":[{"id":9754630,"name":"330 мл","price":0,"promoPrice":null,"multiplier":1},{"id":9754633,"name":"1 л","price":280,"promoPrice":null,"multiplier":1}],"required":true,"minSelected":1,"maxSelected":1}],"picture":null,"weight":"330 мл","promoTypes":[]},{"id":501005,"name":"Минеральная вода Russe Quelle","description":"На выбор с газом или без газа","available":true,"inStock":null,"price":180,"promoPrice":null,"optionsGroups":[{"id":62537,"name":"На выбор","options":[{"id":417871,"name":"С газом","price":0,"promoPrice":null,"multiplier":1},{"id":417873,"name":"Без газа","price":0,"promoPrice":null,"multiplier":1}],"required":true,"minSelected":1,"maxSelected":1},{"id":1440949,"name":"Объем на выбор","options":[{"id":9754636,"name":"250 мл","price":0,"promoPrice":null,"multiplier":1},{"id":9754639,"name":"700 мл","price":110,"promoPrice":null,"multiplier":1}],"required":true,"minSelected":1,"maxSelected":1}],"picture":null,"weight":"250 мл","promoTypes":[]},{"id":501009,"name":"Свежевыжатые соки","description":"На выбор: апельсин, яблоко, грейпфрут, морковь, сельдерей","available":true,"inStock":null,"price":290,"promoPrice":null,"optionsGroups":[{"id":62541,"name":"На выбор","options":[{"id":417879,"name":"Апельсин","price":0,"promoPrice":null,"multiplier":1},{"id":417881,"name":"Яблоко","price":0,"promoPrice":null,"multiplier":1},{"id":417883,"name":"Грейпфрут","price":0,"promoPrice":null,"multiplier":1},{"id":417885,"name":"Морковь","price":0,"promoPrice":null,"multiplier":1},{"id":417887,"name":"Сельдерей","price":0,"promoPrice":null,"multiplier":1}],"required":true,"minSelected":1,"maxSelected":1}],"picture":null,"weight":"200 мл","promoTypes":[]},{"id":500993,"name":"Морс домашний","description":null,"available":true,"inStock":null,"price":180,"promoPrice":null,"optionsGroups":[],"picture":null,"weight":"200 мл","promoTypes":[]},{"id":500997,"name":"Имбирный эль","description":null,"available":true,"inStock":null,"price":180,"promoPrice":null,"optionsGroups":[],"picture":null,"weight":"250 мл","promoTypes":[]},{"id":500999,"name":"Bitter Lemon","description":null,"available":true,"inStock":null,"price":180,"promoPrice":null,"optionsGroups":[],"picture":null,"weight":"250 мл","promoTypes":[]},{"id":501001,"name":"Tonic","description":null,"available":true,"inStock":null,"price":180,"promoPrice":null,"optionsGroups":[],"picture":null,"weight":"250 мл","promoTypes":[]},{"id":501003,"name":"Сок Pago в ассортименте","description":null,"available":true,"inStock":null,"price":180,"promoPrice":null,"optionsGroups":[{"id":62547,"name":"На выбор","options":[{"id":417897,"name":"Апельсиновый","price":0,"promoPrice":null,"multiplier":1},{"id":417899,"name":"Томатный","price":0,"promoPrice":null,"multiplier":1},{"id":417901,"name":"Яблочный","price":0,"promoPrice":null,"multiplier":1},{"id":417903,"name":"Вишневый","price":0,"promoPrice":null,"multiplier":1}],"required":true,"minSelected":1,"maxSelected":1}],"picture":null,"weight":"200 мл","promoTypes":[]}],"categories":[]}]}}}